{
    "created_time": "2020-08-28T06:12:04Z",
    "files": [
        {
            "attachment_folder": "",
            "attachments": [
            ],
            "created_time": "2020-08-28T06:13:14Z",
            "modified_time": "2020-08-28T06:13:23Z",
            "name": "NPM简介.md",
            "tags": [
            ]
        },
        {
            "attachment_folder": "",
            "attachments": [
            ],
            "created_time": "2020-08-28T06:13:44Z",
            "modified_time": "2020-08-28T06:13:59Z",
            "name": "安装所有依赖.md",
            "tags": [
            ]
        },
        {
            "attachment_folder": "",
            "attachments": [
            ],
            "created_time": "2020-08-28T06:14:14Z",
            "modified_time": "2020-08-28T06:14:21Z",
            "name": "安装单个软件包.md",
            "tags": [
            ]
        },
        {
            "attachment_folder": "",
            "attachments": [
            ],
            "created_time": "2020-08-28T06:14:44Z",
            "modified_time": "2020-08-28T06:14:48Z",
            "name": "更新软件包.md",
            "tags": [
            ]
        },
        {
            "attachment_folder": "",
            "attachments": [
            ],
            "created_time": "2020-08-28T06:15:07Z",
            "modified_time": "2020-08-28T06:15:14Z",
            "name": "版本控制.md",
            "tags": [
            ]
        },
        {
            "attachment_folder": "",
            "attachments": [
            ],
            "created_time": "2020-08-28T06:15:28Z",
            "modified_time": "2020-08-28T06:15:31Z",
            "name": "运行任务.md",
            "tags": [
            ]
        },
        {
            "attachment_folder": "",
            "attachments": [
            ],
            "created_time": "2020-08-28T06:16:38Z",
            "modified_time": "2020-08-28T06:16:45Z",
            "name": "npm将包安装到哪里？.md",
            "tags": [
            ]
        },
        {
            "attachment_folder": "",
            "attachments": [
            ],
            "created_time": "2020-08-28T06:17:18Z",
            "modified_time": "2020-08-28T06:17:31Z",
            "name": "如何使用安装的包.md",
            "tags": [
            ]
        },
        {
            "attachment_folder": "",
            "attachments": [
            ],
            "created_time": "2020-08-28T06:18:39Z",
            "modified_time": "2020-08-28T06:20:38Z",
            "name": "package.json 指南 .md",
            "tags": [
            ]
        },
        {
            "attachment_folder": "",
            "attachments": [
            ],
            "created_time": "2020-08-28T06:21:53Z",
            "modified_time": "2020-08-28T06:22:31Z",
            "name": "package-lock.json 文件 .md",
            "tags": [
            ]
        },
        {
            "attachment_folder": "",
            "attachments": [
            ],
            "created_time": "2020-08-28T06:22:40Z",
            "modified_time": "2020-08-28T06:22:59Z",
            "name": "查看npm包安装的版本.md",
            "tags": [
            ]
        },
        {
            "attachment_folder": "",
            "attachments": [
            ],
            "created_time": "2020-08-28T06:23:50Z",
            "modified_time": "2020-08-28T06:23:55Z",
            "name": "安装npm包的旧版本.md",
            "tags": [
            ]
        },
        {
            "attachment_folder": "",
            "attachments": [
            ],
            "created_time": "2020-08-28T06:24:23Z",
            "modified_time": "2020-08-28T06:24:34Z",
            "name": "将所有依赖包更新到最新版本.md",
            "tags": [
            ]
        },
        {
            "attachment_folder": "",
            "attachments": [
            ],
            "created_time": "2020-08-28T06:24:57Z",
            "modified_time": "2020-08-28T06:25:02Z",
            "name": "使用npm的语义版本控制.md",
            "tags": [
            ]
        },
        {
            "attachment_folder": "",
            "attachments": [
            ],
            "created_time": "2020-08-28T06:28:45Z",
            "modified_time": "2020-08-28T06:28:49Z",
            "name": "卸载npm包.md",
            "tags": [
            ]
        },
        {
            "attachment_folder": "",
            "attachments": [
            ],
            "created_time": "2020-08-28T06:29:13Z",
            "modified_time": "2020-08-28T06:29:18Z",
            "name": "全局包和本地包.md",
            "tags": [
            ]
        },
        {
            "attachment_folder": "",
            "attachments": [
            ],
            "created_time": "2020-08-28T06:30:07Z",
            "modified_time": "2020-08-28T06:30:11Z",
            "name": "依赖 与 开发依赖.md",
            "tags": [
            ]
        },
        {
            "attachment_folder": "",
            "attachments": [
            ],
            "created_time": "2020-08-28T06:31:20Z",
            "modified_time": "2020-08-28T06:31:41Z",
            "name": "包运行器 npx.md",
            "tags": [
            ]
        }
    ],
    "sub_directories": [
    ],
    "version": "1"
}
